{
  "VminParameters": {
    "EndVoltageLimits": "1.15",
    "LevelsTc": "IPC::CPU_IP_BASE::cpu_all_bf_x_x_ipc_lvl_min",
    "PatternNameCounterIndexes": "9,10,11,12,13,14,15",
    "SetPointsPlistParamName": "Patlist",
    "SetPointsPlistMode": "Local",
    "StartVoltages": "0.45",
    "RecoveryOptions": "",
    "RecoveryMode": "NoRecovery",
    "StepSize": 0.01,
    "FeatureSwitchSettings": "disable_masked_targets,print_per_target_increments,print_scoreboard_counters,fivr_mode_on",
    "FivrCondition": "NOM_CCF_CORE",
    "TestMode": "SingleVmin",
    "TimingsTc": "IPC::FUN_CCF_CX816::cpu_fun_timing_mts800_tstprtclk400_tck100_fun_ccf",
    "VoltageConverter": "--railconfigurations CDIE_CCF_POWERMUX CDIE_CCF_NBLCTRL --dlvrpins VCCIA --expressions CCF",
    "VoltageTargets": "CCF"
  },
  "Tests": [
    {
      "Name": "F1_1200_MLC_DRG_NONPSEUDO_A",
      "Patlist": "IPC::fun_cdie_vccr_sbft_f2xccf_fc_drg_nonpseudo_1_hptp800_burstoff_list_master",
      "Overrides": {
        "BaseNumbers": "1007",
        "SetPointsPreInstance": "DLVRPS:CCF:PS3,MCdrv:corefreq:1.2GHz,MCdrv:ringfreq_0:1.2GHz",
        "SetPointsPostInstance": "DLVRPS:CCF:PS0",
        "ScoreboardEdgeTicks": 2,
        "ForwardingMode": "Input"
      }
    },
    {
      "Name": "F1_1200_MLC_DRG_NONPSEUDO_B",
      "Patlist": "IPC::fun_cdie_vccr_sbft_f2xccf_fc_drg_nonpseudo_2_hptp800_burstoff_list_master",
      "Overrides": {
        "BaseNumbers": "1008",
        "SetPointsPreInstance": "DLVRPS:CCF:PS3,MCdrv:corefreq:1.2GHz,MCdrv:ringfreq_0:1.2GHz",
        "SetPointsPostInstance": "DLVRPS:CCF:PS0",
        "ScoreboardEdgeTicks": 2,
        "ForwardingMode": "Input"
      }
    },
    {
      "Name": "F1_1200_MLC_DRG_NONPSEUDO_C",
      "Patlist": "IPC::fun_cdie_vccr_sbft_f2xccf_fc_drg_nonpseudo_3_hptp800_burstoff_list_master",
      "Overrides": {
        "BaseNumbers": "1009",
        "SetPointsPreInstance": "DLVRPS:CCF:PS3,MCdrv:corefreq:1.2GHz,MCdrv:ringfreq_0:1.2GHz",
        "SetPointsPostInstance": "DLVRPS:CCF:PS0",
        "ScoreboardEdgeTicks": 2,
        "ForwardingMode": "Input"
      }
    },
    {
      "Name": "F1_1200_MLC_DRG_PSUEDO_A",
      "Patlist": "IPC::fun_cdie_vccr_sbft_f2xccf_fc_drg_pseudo_1_hptp800_burstoff_list_master",
      "Overrides": {
        "BaseNumbers": "1010",
        "SetPointsPreInstance": "DLVRPS:CCF:PS3,MCdrv:corefreq:1.2GHz,MCdrv:ringfreq_0:1.2GHz",
        "SetPointsPostInstance": "DLVRPS:CCF:PS0",
        "ScoreboardEdgeTicks": 2,
        "ForwardingMode": "Input"
      }
    },
    {
      "Name": "F1_1200_MLC_DRG_PSUEDO_B",
      "Patlist": "IPC::fun_cdie_vccr_sbft_f2xccf_fc_drg_pseudo_2_hptp800_burstoff_list_master",
      "Overrides": {
        "BaseNumbers": "1011",
        "SetPointsPreInstance": "DLVRPS:CCF:PS3,MCdrv:corefreq:1.2GHz,MCdrv:ringfreq_0:1.2GHz",
        "SetPointsPostInstance": "DLVRPS:CCF:PS0",
        "ScoreboardEdgeTicks": 2,
        "ForwardingMode": "Input"
      }
    },
    {
      "Name": "F1_1200_MLC_DRG_PSUEDO_C",
      "Patlist": "IPC::fun_cdie_vccr_sbft_f2xccf_fc_drg_pseudo_3_hptp800_burstoff_list_master",
      "Overrides": {
        "BaseNumbers": "1012",
        "SetPointsPreInstance": "DLVRPS:CCF:PS3,MCdrv:corefreq:1.2GHz,MCdrv:ringfreq_0:1.2GHz",
        "SetPointsPostInstance": "DLVRPS:CCF:PS0",
        "ScoreboardEdgeTicks": 2,
        "ForwardingMode": "Input"
      }
    },
    {
      "Name": "F2_2400_MLC_DRG_NONPSEUDO_A",
      "Patlist": "IPC::fun_cdie_vccr_sbft_f2xccf_fc_drg_nonpseudo_1_hptp800_burstoff_list_master",
      "Overrides": {
        "BaseNumbers": "1012",
        "SetPointsPreInstance": "DLVRPS:CCF:PS2,MCdrv:corefreq:1.2GHz,MCdrv:ringfreq_0:2.4GHz",
        "SetPointsPostInstance": "DLVRPS:CCF:PS0",
        "ScoreboardEdgeTicks": 2,
        "ForwardingMode": "Input"
      }
    },
    {
      "Name": "F2_2400_MLC_DRG_NONPSEUDO_B",
      "Patlist": "IPC::fun_cdie_vccr_sbft_f2xccf_fc_drg_nonpseudo_2_hptp800_burstoff_list_master",
      "Overrides": {
        "BaseNumbers": "1013",
        "SetPointsPreInstance": "DLVRPS:CCF:PS2,MCdrv:corefreq:1.2GHz,MCdrv:ringfreq_0:2.4GHz",
        "SetPointsPostInstance": "DLVRPS:CCF:PS0",
        "ScoreboardEdgeTicks": 2,
        "ForwardingMode": "Input"
      }
    },
    {
      "Name": "F2_2400_MLC_DRG_NONPSEUDO_C",
      "Patlist": "IPC::fun_cdie_vccr_sbft_f2xccf_fc_drg_nonpseudo_3_hptp800_burstoff_list_master",
      "Overrides": {
        "BaseNumbers": "1014",
        "SetPointsPreInstance": "DLVRPS:CCF:PS2,MCdrv:corefreq:1.2GHz,MCdrv:ringfreq_0:2.4GHz",
        "SetPointsPostInstance": "DLVRPS:CCF:PS0",
        "ScoreboardEdgeTicks": 2,
        "ForwardingMode": "Input"
      }
    },
    {
      "Name": "F2_2400_MLC_DRG_PSUEDO_A",
      "Patlist": "IPC::fun_cdie_vccr_sbft_f2xccf_fc_drg_pseudo_1_hptp800_burstoff_list_master",
      "Overrides": {
        "BaseNumbers": "1015",
        "SetPointsPreInstance": "DLVRPS:CCF:PS2,MCdrv:corefreq:1.2GHz,MCdrv:ringfreq_0:2.4GHz",
        "SetPointsPostInstance": "DLVRPS:CCF:PS0",
        "ScoreboardEdgeTicks": 2,
        "ForwardingMode": "Input"
      }
    },
    {
      "Name": "F2_2400_MLC_DRG_PSUEDO_B",
      "Patlist": "IPC::fun_cdie_vccr_sbft_f2xccf_fc_drg_pseudo_2_hptp800_burstoff_list_master",
      "Overrides": {
        "BaseNumbers": "1016",
        "SetPointsPreInstance": "DLVRPS:CCF:PS2,MCdrv:corefreq:1.2GHz,MCdrv:ringfreq_0:2.4GHz",
        "SetPointsPostInstance": "DLVRPS:CCF:PS0",
        "ScoreboardEdgeTicks": 2,
        "ForwardingMode": "Input"
      }
    },
    {
      "Name": "F2_2400_MLC_DRG_PSUEDO_C",
      "Patlist": "IPC::fun_cdie_vccr_sbft_f2xccf_fc_drg_pseudo_3_hptp800_burstoff_list_master",
      "Overrides": {
        "BaseNumbers": "1017",
        "SetPointsPreInstance": "DLVRPS:CCF:PS2,MCdrv:corefreq:1.2GHz,MCdrv:ringfreq_0:2.4GHz",
        "SetPointsPostInstance": "DLVRPS:CCF:PS0",
        "ScoreboardEdgeTicks": 2,
        "ForwardingMode": "Input"
      }
    },
    {
      "Name": "F3_3400_MLC_DRG_NONPSEUDO_A",
      "Patlist": "IPC::fun_cdie_vccr_sbft_f2xccf_fc_drg_nonpseudo_1_hptp800_burstoff_list_master",
      "Overrides": {
        "BaseNumbers": "1017",
        "SetPointsPreInstance": "DLVRPS:CCF:PS1,MCdrv:corefreq:1.2GHz,MCdrv:ringfreq_0:3.4GHz",
        "SetPointsPostInstance": "DLVRPS:CCF:PS0",
        "ScoreboardEdgeTicks": 2,
        "ForwardingMode": "Input"
      }
    },
    {
      "Name": "F3_3400_MLC_DRG_NONPSEUDO_B",
      "Patlist": "IPC::fun_cdie_vccr_sbft_f2xccf_fc_drg_nonpseudo_2_hptp800_burstoff_list_master",
      "Overrides": {
        "BaseNumbers": "1018",
        "SetPointsPreInstance": "DLVRPS:CCF:PS1,MCdrv:corefreq:1.2GHz,MCdrv:ringfreq_0:3.4GHz",
        "SetPointsPostInstance": "DLVRPS:CCF:PS0",
        "ScoreboardEdgeTicks": 2,
        "ForwardingMode": "Input"
      }
    },
    {
      "Name": "F3_3400_MLC_DRG_NONPSEUDO_C",
      "Patlist": "IPC::fun_cdie_vccr_sbft_f2xccf_fc_drg_nonpseudo_3_hptp800_burstoff_list_master",
      "Overrides": {
        "BaseNumbers": "1019",
        "SetPointsPreInstance": "DLVRPS:CCF:PS1,MCdrv:corefreq:1.2GHz,MCdrv:ringfreq_0:3.4GHz",
        "SetPointsPostInstance": "DLVRPS:CCF:PS0",
        "ScoreboardEdgeTicks": 2,
        "ForwardingMode": "Input"
      }
    },
    {
      "Name": "F3_3400_MLC_DRG_PSUEDO_A",
      "Patlist": "IPC::fun_cdie_vccr_sbft_f2xccf_fc_drg_pseudo_1_hptp800_burstoff_list_master",
      "Overrides": {
        "BaseNumbers": "1020",
        "SetPointsPreInstance": "DLVRPS:CCF:PS1,MCdrv:corefreq:1.2GHz,MCdrv:ringfreq_0:3.4GHz",
        "SetPointsPostInstance": "DLVRPS:CCF:PS0",
        "ScoreboardEdgeTicks": 2,
        "ForwardingMode": "Input"
      }
    },
    {
      "Name": "F3_3400_MLC_DRG_PSUEDO_B",
      "Patlist": "IPC::fun_cdie_vccr_sbft_f2xccf_fc_drg_pseudo_2_hptp800_burstoff_list_master",
      "Overrides": {
        "BaseNumbers": "1021",
        "SetPointsPreInstance": "DLVRPS:CCF:PS1,MCdrv:corefreq:1.2GHz,MCdrv:ringfreq_0:3.4GHz",
        "SetPointsPostInstance": "DLVRPS:CCF:PS0",
        "ScoreboardEdgeTicks": 2,
        "ForwardingMode": "Input"
      }
    },
    {
      "Name": "F3_3400_MLC_DRG_PSUEDO_C",
      "Patlist": "IPC::fun_cdie_vccr_sbft_f2xccf_fc_drg_pseudo_3_hptp800_burstoff_list_master",
      "Overrides": {
        "BaseNumbers": "1022",
        "SetPointsPreInstance": "DLVRPS:CCF:PS1,MCdrv:corefreq:1.2GHz,MCdrv:ringfreq_0:3.4GHz",
        "SetPointsPostInstance": "DLVRPS:CCF:PS0",
        "ScoreboardEdgeTicks": 2,
        "ForwardingMode": "Input"
      }
    },
    {
      "Name": "F4_4000_MLC_DRG_1100_NONPSEUDO_A",
      "Patlist": "IPC::fun_cdie_vccr_sbft_f2xccf_fc_drg_nonpseudo_1_hptp800_burstoff_list_master",
      "Overrides": {
        "BaseNumbers": "1022",
        "SetPointsPreInstance": "DLVRPS:CCF:PS1,MCdrv:corefreq:1.2GHz,MCdrv:ringfreq_0:4.0GHz",
        "SetPointsPostInstance": "DLVRPS:CCF:PS0",
        "ScoreboardEdgeTicks": 2,
        "ForwardingMode": "Input"
      }
    },
    {
      "Name": "F4_4000_MLC_DRG_1100_NONPSEUDO_B",
      "Patlist": "IPC::fun_cdie_vccr_sbft_f2xccf_fc_drg_nonpseudo_2_hptp800_burstoff_list_master",
      "Overrides": {
        "BaseNumbers": "1023",
        "SetPointsPreInstance": "DLVRPS:CCF:PS1,MCdrv:corefreq:1.2GHz,MCdrv:ringfreq_0:4.0GHz",
        "SetPointsPostInstance": "DLVRPS:CCF:PS0",
        "ScoreboardEdgeTicks": 2,
        "ForwardingMode": "Input"
      }
    },
    {
      "Name": "F4_4000_MLC_DRG_1100_NONPSEUDO_C",
      "Patlist": "IPC::fun_cdie_vccr_sbft_f2xccf_fc_drg_nonpseudo_3_hptp800_burstoff_list_master",
      "Overrides": {
        "BaseNumbers": "1024",
        "SetPointsPreInstance": "DLVRPS:CCF:PS1,MCdrv:corefreq:1.2GHz,MCdrv:ringfreq_0:4.0GHz",
        "SetPointsPostInstance": "DLVRPS:CCF:PS0",
        "ScoreboardEdgeTicks": 2,
        "ForwardingMode": "Input"
      }
    },
    {
      "Name": "F4_4000_MLC_DRG_1100_PSUEDO_A",
      "Patlist": "IPC::fun_cdie_vccr_sbft_f2xccf_fc_drg_pseudo_1_hptp800_burstoff_list_master",
      "Overrides": {
        "BaseNumbers": "1025",
        "SetPointsPreInstance": "DLVRPS:CCF:PS1,MCdrv:corefreq:1.2GHz,MCdrv:ringfreq_0:4.0GHz",
        "SetPointsPostInstance": "DLVRPS:CCF:PS0",
        "ScoreboardEdgeTicks": 2,
        "ForwardingMode": "Input"
      }
    },
    {
      "Name": "F4_4000_MLC_DRG_1100_PSUEDO_B",
      "Patlist": "IPC::fun_cdie_vccr_sbft_f2xccf_fc_drg_pseudo_2_hptp800_burstoff_list_master",
      "Overrides": {
        "BaseNumbers": "1026",
        "SetPointsPreInstance": "DLVRPS:CCF:PS1,MCdrv:corefreq:1.2GHz,MCdrv:ringfreq_0:4.0GHz",
        "SetPointsPostInstance": "DLVRPS:CCF:PS0",
        "ScoreboardEdgeTicks": 2,
        "ForwardingMode": "Input"
      }
    },
    {
      "Name": "F4_4000_MLC_DRG_1100_PSUEDO_C",
      "Patlist": "IPC::fun_cdie_vccr_sbft_f2xccf_fc_drg_pseudo_3_hptp800_burstoff_list_master",
      "Overrides": {
        "BaseNumbers": "1027",
        "SetPointsPreInstance": "DLVRPS:CCF:PS1,MCdrv:corefreq:1.2GHz,MCdrv:ringfreq_0:4.0GHz",
        "SetPointsPostInstance": "DLVRPS:CCF:PS0",
        "ScoreboardEdgeTicks": 2,
        "ForwardingMode": "Input"
      }
    },
    {
      "Name": "F5_4100_MLC_DRG_1100_NONPSEUDO_A",
      "Patlist": "IPC::fun_cdie_vccr_sbft_f2xccf_fc_drg_nonpseudo_1_hptp800_burstoff_list_master",
      "Overrides": {
        "BaseNumbers": "1027",
        "SetPointsPreInstance": "DLVRPS:CCF:PS1,MCdrv:corefreq:1.2GHz,MCdrv:ringfreq_0:4.1GHz",
        "SetPointsPostInstance": "DLVRPS:CCF:PS0",
        "ScoreboardEdgeTicks": 2,
        "ForwardingMode": "Input"
      }
    },
    {
      "Name": "F5_4100_MLC_DRG_1100_NONPSEUDO_B",
      "Patlist": "IPC::fun_cdie_vccr_sbft_f2xccf_fc_drg_nonpseudo_2_hptp800_burstoff_list_master",
      "Overrides": {
        "BaseNumbers": "1028",
        "SetPointsPreInstance": "DLVRPS:CCF:PS1,MCdrv:corefreq:1.2GHz,MCdrv:ringfreq_0:4.1GHz",
        "SetPointsPostInstance": "DLVRPS:CCF:PS0",
        "ScoreboardEdgeTicks": 2,
        "ForwardingMode": "Input"
      }
    },
    {
      "Name": "F5_4100_MLC_DRG_1100_NONPSEUDO_C",
      "Patlist": "IPC::fun_cdie_vccr_sbft_f2xccf_fc_drg_nonpseudo_3_hptp800_burstoff_list_master",
      "Overrides": {
        "BaseNumbers": "1029",
        "SetPointsPreInstance": "DLVRPS:CCF:PS1,MCdrv:corefreq:1.2GHz,MCdrv:ringfreq_0:4.1GHz",
        "SetPointsPostInstance": "DLVRPS:CCF:PS0",
        "ScoreboardEdgeTicks": 2,
        "ForwardingMode": "Input"
      }
    },
    {
      "Name": "F5_4100_MLC_DRG_1100_PSUEDO_A",
      "Patlist": "IPC::fun_cdie_vccr_sbft_f2xccf_fc_drg_pseudo_1_hptp800_burstoff_list_master",
      "Overrides": {
        "BaseNumbers": "1030",
        "SetPointsPreInstance": "DLVRPS:CCF:PS1,MCdrv:corefreq:1.2GHz,MCdrv:ringfreq_0:4.1GHz",
        "SetPointsPostInstance": "DLVRPS:CCF:PS0",
        "ScoreboardEdgeTicks": 2,
        "ForwardingMode": "Input"
      }
    },
    {
      "Name": "F5_4100_MLC_DRG_1100_PSUEDO_B",
      "Patlist": "IPC::fun_cdie_vccr_sbft_f2xccf_fc_drg_pseudo_2_hptp800_burstoff_list_master",
      "Overrides": {
        "BaseNumbers": "1031",
        "SetPointsPreInstance": "DLVRPS:CCF:PS1,MCdrv:corefreq:1.2GHz,MCdrv:ringfreq_0:4.1GHz",
        "SetPointsPostInstance": "DLVRPS:CCF:PS0",
        "ScoreboardEdgeTicks": 2,
        "ForwardingMode": "Input"
      }
    },
    {
      "Name": "F5_4100_MLC_DRG_1100_PSUEDO_C",
      "Patlist": "IPC::fun_cdie_vccr_sbft_f2xccf_fc_drg_pseudo_3_hptp800_burstoff_list_master",
      "Overrides": {
        "BaseNumbers": "1032",
        "SetPointsPreInstance": "DLVRPS:CCF:PS1,MCdrv:corefreq:1.2GHz,MCdrv:ringfreq_0:4.1GHz",
        "SetPointsPostInstance": "DLVRPS:CCF:PS0",
        "ScoreboardEdgeTicks": 2,
        "ForwardingMode": "Input"
      }
    },
    {
      "Name": "F6_4300_MLC_DRG_1100_NONPSEUDO_A",
      "Patlist": "IPC::fun_cdie_vccr_sbft_f2xccf_fc_drg_nonpseudo_1_hptp800_burstoff_list_master",
      "Overrides": {
        "BaseNumbers": "1032",
        "SetPointsPreInstance": "DLVRPS:CCF:PS1,MCdrv:corefreq:1.2GHz,MCdrv:ringfreq_0:4.3GHz",
        "SetPointsPostInstance": "DLVRPS:CCF:PS0",
        "ScoreboardEdgeTicks": 2,
        "ForwardingMode": "Input"
      }
    },
    {
      "Name": "F6_4300_MLC_DRG_1100_NONPSEUDO_B",
      "Patlist": "IPC::fun_cdie_vccr_sbft_f2xccf_fc_drg_nonpseudo_2_hptp800_burstoff_list_master",
      "Overrides": {
        "BaseNumbers": "1033",
        "SetPointsPreInstance": "DLVRPS:CCF:PS1,MCdrv:corefreq:1.2GHz,MCdrv:ringfreq_0:4.3GHz",
        "SetPointsPostInstance": "DLVRPS:CCF:PS0",
        "ScoreboardEdgeTicks": 2,
        "ForwardingMode": "Input"
      }
    },
    {
      "Name": "F6_4300_MLC_DRG_1100_NONPSEUDO_C",
      "Patlist": "IPC::fun_cdie_vccr_sbft_f2xccf_fc_drg_nonpseudo_3_hptp800_burstoff_list_master",
      "Overrides": {
        "BaseNumbers": "1034",
        "SetPointsPreInstance": "DLVRPS:CCF:PS1,MCdrv:corefreq:1.2GHz,MCdrv:ringfreq_0:4.3GHz",
        "SetPointsPostInstance": "DLVRPS:CCF:PS0",
        "ScoreboardEdgeTicks": 2,
        "ForwardingMode": "Input"
      }
    },
    {
      "Name": "F6_4300_MLC_DRG_1100_PSUEDO_A",
      "Patlist": "IPC::fun_cdie_vccr_sbft_f2xccf_fc_drg_pseudo_1_hptp800_burstoff_list_master",
      "Overrides": {
        "BaseNumbers": "1035",
        "SetPointsPreInstance": "DLVRPS:CCF:PS1,MCdrv:corefreq:1.2GHz,MCdrv:ringfreq_0:4.3GHz",
        "SetPointsPostInstance": "DLVRPS:CCF:PS0",
        "ScoreboardEdgeTicks": 2,
        "ForwardingMode": "Input"
      }
    },
    {
      "Name": "F6_4300_MLC_DRG_1100_PSUEDO_B",
      "Patlist": "IPC::fun_cdie_vccr_sbft_f2xccf_fc_drg_pseudo_2_hptp800_burstoff_list_master",
      "Overrides": {
        "BaseNumbers": "1036",
        "SetPointsPreInstance": "DLVRPS:CCF:PS1,MCdrv:corefreq:1.2GHz,MCdrv:ringfreq_0:4.3GHz",
        "SetPointsPostInstance": "DLVRPS:CCF:PS0",
        "ScoreboardEdgeTicks": 2,
        "ForwardingMode": "Input"
      }
    },
    {
      "Name": "F6_4300_MLC_DRG_1100_PSUEDO_C",
      "Patlist": "IPC::fun_cdie_vccr_sbft_f2xccf_fc_drg_pseudo_3_hptp800_burstoff_list_master",
      "Overrides": {
        "BaseNumbers": "1037",
        "SetPointsPreInstance": "DLVRPS:CCF:PS1,MCdrv:corefreq:1.2GHz,MCdrv:ringfreq_0:4.3GHz",
        "SetPointsPostInstance": "DLVRPS:CCF:PS0",
        "ScoreboardEdgeTicks": 2,
        "ForwardingMode": "Input"
      }
    },
    {
      "Name": "F7_4600_MLC_DRG_1100_NONPSEUDO_A",
      "Patlist": "IPC::fun_cdie_vccr_sbft_f2xccf_fc_drg_nonpseudo_1_hptp800_burstoff_list_master",
      "Overrides": {
        "BaseNumbers": "1036",
        "SetPointsPreInstance": "DLVRPS:CCF:PS1,MCdrv:corefreq:1.2GHz,MCdrv:ringfreq_0:4.6GHz",
        "SetPointsPostInstance": "DLVRPS:CCF:PS0",
        "ScoreboardEdgeTicks": 2,
        "ForwardingMode": "Input"
      }
    },
    {
      "Name": "F7_4600_MLC_DRG_1100_NONPSEUDO_B",
      "Patlist": "IPC::fun_cdie_vccr_sbft_f2xccf_fc_drg_nonpseudo_2_hptp800_burstoff_list_master",
      "Overrides": {
        "BaseNumbers": "1037",
        "SetPointsPreInstance": "DLVRPS:CCF:PS1,MCdrv:corefreq:1.2GHz,MCdrv:ringfreq_0:4.6GHz",
        "SetPointsPostInstance": "DLVRPS:CCF:PS0",
        "ScoreboardEdgeTicks": 2,
        "ForwardingMode": "Input"
      }
    },
    {
      "Name": "F7_4600_MLC_DRG_1100_NONPSEUDO_C",
      "Patlist": "IPC::fun_cdie_vccr_sbft_f2xccf_fc_drg_nonpseudo_3_hptp800_burstoff_list_master",
      "Overrides": {
        "BaseNumbers": "1038",
        "SetPointsPreInstance": "DLVRPS:CCF:PS1,MCdrv:corefreq:1.2GHz,MCdrv:ringfreq_0:4.6GHz",
        "SetPointsPostInstance": "DLVRPS:CCF:PS0",
        "ScoreboardEdgeTicks": 2,
        "ForwardingMode": "Input"
      }
    },
    {
      "Name": "F7_4600_MLC_DRG_1100_PSUEDO_A",
      "Patlist": "IPC::fun_cdie_vccr_sbft_f2xccf_fc_drg_pseudo_1_hptp800_burstoff_list_master",
      "Overrides": {
        "BaseNumbers": "1039",
        "SetPointsPreInstance": "DLVRPS:CCF:PS1,MCdrv:corefreq:1.2GHz,MCdrv:ringfreq_0:4.6GHz",
        "SetPointsPostInstance": "DLVRPS:CCF:PS0",
        "ScoreboardEdgeTicks": 2,
        "ForwardingMode": "Input"
      }
    },
    {
      "Name": "F7_4600_MLC_DRG_1100_PSUEDO_B",
      "Patlist": "IPC::fun_cdie_vccr_sbft_f2xccf_fc_drg_pseudo_2_hptp800_burstoff_list_master",
      "Overrides": {
        "BaseNumbers": "1040",
        "SetPointsPreInstance": "DLVRPS:CCF:PS1,MCdrv:corefreq:1.2GHz,MCdrv:ringfreq_0:4.6GHz",
        "SetPointsPostInstance": "DLVRPS:CCF:PS0",
        "ScoreboardEdgeTicks": 2,
        "ForwardingMode": "Input"
      }
    },
    {
      "Name": "F7_4600_MLC_DRG_1100_PSUEDO_C",
      "Patlist": "IPC::fun_cdie_vccr_sbft_f2xccf_fc_drg_pseudo_3_hptp800_burstoff_list_master",
      "Overrides": {
        "BaseNumbers": "1041",
        "SetPointsPreInstance": "DLVRPS:CCF:PS1,MCdrv:corefreq:1.2GHz,MCdrv:ringfreq_0:4.6GHz",
        "SetPointsPostInstance": "DLVRPS:CCF:PS0",
        "ScoreboardEdgeTicks": 2,
        "ForwardingMode": "Input"
      }
    }
  ]
}