{
    "Groups": [
        {
            "Default": "L0",
            "Name": "L2_SLEEP",
            "SetPoints": [
                {
                    "Configurations": [
                        {
							"Data": "0",
                            "Name": "L2_SLEEP"
                        }
                    ],
					"Name": "L0"
                },
                {
                    "Configurations": [
                        {
							"Data": "1",
                            "Name": "L2_SLEEP"
                        }
                    ],
					"Name": "L1"
                }
            ]
        }
    ],
    "Module": "MCAscn"
}